wasm_import/__init__.py
wasm_import/sprintf.py
wasm_import-0.1.1.dist-info/LICENSE
wasm_import-0.1.1.dist-info/METADATA
wasm_import-0.1.1.dist-info/WHEEL
wasm_import-0.1.1.dist-info/top_level.txt
wasm_import-0.1.1.dist-info/RECORD
