Metadata-Version: 2.1
Name: wasm-import
Version: 0.1.1
Summary: printf function for Python Web Assembly runtime
Home-page: https://github.com/kign/pkg-wasm-import
Author: Konstantin Ignatiev
Author-email: kostya@inet-lab.net
License: UNKNOWN
Project-URL: Bug Tracker, https://github.com/kign/pkg-wasm-import/issues
Platform: UNKNOWN
Classifier: Programming Language :: Python :: 3
Classifier: License :: OSI Approved :: GNU General Public License v2 (GPLv2)
Classifier: Operating System :: OS Independent
Requires-Python: >=3.7
License-File: LICENSE
